wincalcbindings.cpython-312-darwin.so
pywincalc/__init__.py
pywincalc/standards/ASTM E308 1931 X.dsp
pywincalc/standards/ASTM E308 1931 X.loc
pywincalc/standards/ASTM E308 1931 Y.dsp
pywincalc/standards/ASTM E308 1931 Y.loc
pywincalc/standards/ASTM E308 1931 Z.dsp
pywincalc/standards/ASTM E308 1964 X.dsp
pywincalc/standards/ASTM E308 1964 X.loc
pywincalc/standards/ASTM E308 1964 Y.dsp
pywincalc/standards/ASTM E308 1964 Y.loc
pywincalc/standards/ASTM E308 1964 Z.dsp
pywincalc/standards/ASTM E308 Illuminant A.ssp
pywincalc/standards/ASTM E308 Illuminant C.ssp
pywincalc/standards/ASTM E308 Illuminant D50.ssp
pywincalc/standards/ASTM E308 Illuminant D55.ssp
pywincalc/standards/ASTM E308 Illuminant D65.ssp
pywincalc/standards/ASTM E308 Table 5-1 X.ssp
pywincalc/standards/ASTM E308 Table 5-1 Y.ssp
pywincalc/standards/ASTM E308 Table 5-1 Z.ssp
pywincalc/standards/ASTM E308 Table 5-19 X.ssp
pywincalc/standards/ASTM E308 Table 5-19 Y.ssp
pywincalc/standards/ASTM E308 Table 5-19 Z.ssp
pywincalc/standards/ASTM E891 Table 1 Direct AM1_5.ssp
pywincalc/standards/ASTM E891 Table3 50 Sel Ord AM1_5.ssp
pywincalc/standards/ASTM G173 AM1_5 37 Tilt Direct Full Spectrum.ssp
pywincalc/standards/ASTM G173 AM1_5 37 Tilt Global Full Spectrum.ssp
pywincalc/standards/ASTM G197 AM1_5 20 Tilt Direct Full Spectrum.ssp
pywincalc/standards/ASTM G197 AM1_5 20 Tilt Global Full Spectrum.ssp
pywincalc/standards/ASTM G197 AM1_5 90 Tilt Direct Full Spectrum.ssp
pywincalc/standards/ASTM G197 AM1_5 90 Tilt Global Full Spectrum.ssp
pywincalc/standards/CIE 1931 1nm X.dsp
pywincalc/standards/CIE 1931 1nm X.loc
pywincalc/standards/CIE 1931 1nm Y.dsp
pywincalc/standards/CIE 1931 1nm Y.loc
pywincalc/standards/CIE 1931 1nm Z.dsp
pywincalc/standards/CIE 1931 5nm X.dsp
pywincalc/standards/CIE 1931 5nm X.loc
pywincalc/standards/CIE 1931 5nm Y.dsp
pywincalc/standards/CIE 1931 5nm Y.loc
pywincalc/standards/CIE 1931 5nm Z.dsp
pywincalc/standards/CIE 1964 1nm X.dsp
pywincalc/standards/CIE 1964 1nm X.loc
pywincalc-3.6.2.dist-info/LICENSE
pywincalc-3.6.2.dist-info/METADATA
pywincalc-3.6.2.dist-info/WHEEL
pywincalc-3.6.2.dist-info/top_level.txt
pywincalc-3.6.2.dist-info/RECORD
