Metadata-Version: 2.1
Name: pywincalc
Version: 3.6.2
Summary: A Python library for calculating thermal and optical properties of glazing systems
Home-page: https://github.com/LBNL-ETA/pywincalc
Author: LBNL
Author-email: sczarnecki@lbl.gov
License: BSD 3-clause
Platform: UNKNOWN
Requires-Dist: deprecation
